{"api.md":"D6-h5422","api_async.md":"yycybcfO","api_config.md":"Czf7JtiU","api_http.md":"BcE1wwr6","api_index.md":"moq6JDGl","api_json.md":"ByFg6LUT","api_middleware.md":"BPSHiCVD","api_p2p.md":"CaTEu2c_","api_websocket.md":"CSMLBxPC","examples_api-key.md":"Cxfiyixc","examples_async.md":"Cyt-p39c","examples_auth.md":"DnNxYN4Z","examples_batch-insert-tx.md":"vMfxFToB","examples_body-limit.md":"SXhB_CfS","examples_caching.md":"DaAoNV3a","examples_compression.md":"Dmy1NIz3","examples_cookies.md":"B8InnQn-","examples_cors.md":"DG1R9jWI","examples_csrf.md":"iAVM7cIX","examples_db-production-guide.md":"DK_e9oMy","examples_db-quickstart.md":"oZk8IIoE","examples_db-transactions.md":"BsxjgdM2","examples_db.md":"BQiYWgNq","examples_error-handling.md":"BP7E_Mtv","examples_errors.md":"DP9_9eeH","examples_etag.md":"Co9w8kWm","examples_form.md":"C7j1cK0R","examples_graceful-shutdown.md":"JqWUcL8q","examples_group-advanced-patterns.md":"DseBKEKl","examples_group-api.md":"BweaBRAk","examples_group-vs-prefix.md":"CH9bgobQ","examples_headers.md":"Cnw3whhT","examples_hello-http.md":"1b2Be_yN","examples_index.md":"DlsBjTDx","examples_ip-filter.md":"DzsXxpda","examples_json-basics.md":"3sA12ija","examples_json-parsers.md":"BYuPvgz3","examples_jwt.md":"s7EcH8VW","examples_logging-json.md":"B6XcPbi7","examples_middleware.md":"BWCIW0PV","examples_migrations.md":"DkGw2Xkh","examples_multipart.md":"BH4FCZbp","examples_notifications.md":"BVftLRte","examples_openapi.md":"DgJSbm46","examples_outbox.md":"D7f4WG0S","examples_p2p-http.md":"HkNamwtJ","examples_p2p-node.md":"DiCCAEGW","examples_p2p-sync.md":"BZowVIfE","examples_presence.md":"CjCkwaTJ","examples_production-api-groups.md":"B6f1GCEA","examples_querybuilder-update.md":"CS55pQvw","examples_rate-limit.md":"DoaPUzBu","examples_rbac-session.md":"CSsYoQLB","examples_rbac.md":"gpwz7DMQ","examples_realtime.md":"BHjzr8tY","examples_repository-crud-full.md":"rXPkIpUK","examples_rest-api.md":"b_hfpSE4","examples_retry-policy.md":"BJypwtr5","examples_routing.md":"ChBjTLM-","examples_session-advanced.md":"BJ_8Vpsh","examples_session-jwt.md":"C0jRVg8p","examples_session.md":"DJmlz5C_","examples_static-files.md":"YBhca8p6","examples_streaming.md":"XN-8R5zR","examples_sync.md":"D5LJcd4C","examples_tx-unit-of-work.md":"yobwOJde","examples_users-crud.md":"DwIX8TS5","examples_validation.md":"4XvxgWFH","examples_wal-recovery.md":"CpomRtHR","examples_ws-chat.md":"DWHBpnvs","fundamentals_errors.md":"CKGUh7hJ","fundamentals_index.md":"0vV7C45X","fundamentals_lifecycle.md":"BorG27eG","fundamentals_logging.md":"qQSA06eU","fundamentals_performance.md":"C3vXC8rQ","fundamentals_security.md":"x-fbI01C","guide.md":"BLpfyyyi","index.md":"CcBM3vEP","inference_index.md":"8MUXVpR5","inference_providers.md":"BukoKk-X","inference_reliability.md":"DRcQVN-5","inference_routing.md":"C-rkS-pm","inference_streaming.md":"CenEhmgZ","install.md":"C3Gsv-FM","modules_async_api.md":"CFQgb3cT","modules_async_asio.md":"Cuni3L45","modules_async_cancel.md":"BF7eeFJU","modules_async_dns.md":"CmZo-Nje","modules_async_error.md":"BPqrEIZt","modules_async_example.md":"9jgg31_T","modules_async_index.md":"DjtZePUj","modules_async_io.md":"Bj0W9QFW","modules_async_scheduler.md":"BtkE17Y9","modules_async_signal.md":"Jt4ddDXm","modules_async_spawn.md":"CT9WxYhJ","modules_async_task.md":"CVHIzdh_","modules_async_tcp.md":"BXxZfEMY","modules_async_threadpool.md":"BzM1GSoo","modules_async_timer.md":"DX0x00fm","modules_async_udp.md":"DulZFKcf","modules_async_when.md":"Dregcuef","modules_cache_guide.md":"BAPodfcg","modules_cache_index.md":"VNRZQKF5","modules_cli_add.md":"CGiWrv20","modules_cli_build.md":"BRY0sQKS","modules_cli_deps.md":"kmF9R4Ao","modules_cli_dev.md":"ClelgL1p","modules_cli_index.md":"DQ7aWc5m","modules_cli_install.md":"Da_8VNWm","modules_cli_list.md":"BXw64ndq","modules_cli_modules.md":"B1APTGFr","modules_cli_new.md":"DLck3DKU","modules_cli_orm.md":"CBTU_rtV","modules_cli_p2p.md":"NUGkMLfS","modules_cli_pack.md":"DspgJ_xj","modules_cli_publish.md":"CHHNW2Aa","modules_cli_registry.md":"DYrpfoqj","modules_cli_remove.md":"D8t4Z_kK","modules_cli_repl.md":"DGCbgKvq","modules_cli_run.md":"Cp0u8ZHv","modules_cli_search.md":"g82hSWOh","modules_cli_tests.md":"BE1Pi_52","modules_cli_verify.md":"Bw7Y7K7I","modules_conversion_error.md":"B7KjFEKu","modules_conversion_expected.md":"vMje1UiE","modules_conversion_index.md":"J1wePbtL","modules_conversion_parse.md":"DndCZlVV","modules_conversion_to_bool.md":"By8bHCd1","modules_conversion_to_enum.md":"DLmZYIyI","modules_conversion_to_float.md":"DTKhrVEA","modules_conversion_to_int.md":"RzzaXV1E","modules_conversion_to_string.md":"Dip2vQ4_","modules_core_api.md":"Q2NELCBl","modules_core_app.md":"CNrSNvbJ","modules_core_config.md":"CVlG0iOK","modules_core_console.md":"_k7Nu794","modules_core_example.md":"CFdk9OtA","modules_core_executor.md":"BTrVulZQ","modules_core_experimental.md":"DcGV19Np","modules_core_guide.md":"DYczC3op","modules_core_http.md":"DYb7eSEQ","modules_core_index.md":"uFMyXy55","modules_core_middleware.md":"NVN02JoG","modules_core_openapi.md":"UOCBfpGi","modules_core_router.md":"CTZ1sZZA","modules_core_routing.md":"Bmx6Qtr8","modules_core_server.md":"BDnkbZ1v","modules_core_session.md":"BH4XUqxc","modules_core_threadpool.md":"BVoKOgCs","modules_core_timers.md":"DskSBL7o","modules_crypto_guide.md":"DJXCGfGK","modules_crypto_index.md":"CSkcYr7i","modules_db_guide.md":"4ffRDeb4","modules_db_index.md":"LTxCCOYp","modules_deploy_guide.md":"8o6H9asr","modules_deploy_index.md":"CuLgQQ7E","modules_json_build.md":"xw7ww24E","modules_json_convert.md":"BtBro9I8","modules_json_dumps.md":"Chl311o_","modules_json_index.md":"CIW7mMAG","modules_json_jpath.md":"CUnrY21f","modules_json_loads.md":"DcLWoR5g","modules_json_simple.md":"DkhTheVE","modules_middleware_guide.md":"CZxCq-L1","modules_middleware_index.md":"CrjYYl0S","modules_net_guide.md":"CZOQNHT0","modules_net_index.md":"Dm5ut8Tm","modules_orm_examples.md":"BIeVD7Bi","modules_orm_index.md":"C4XYcbIu","modules_orm_repository.md":"BM_1JEYd","modules_p2p_api.md":"DZngV3D4","modules_p2p_guide.md":"CGud_TYV","modules_p2p_http_guide.md":"9JX-RNZa","modules_p2p_http_index.md":"NudGUBOu","modules_p2p_index.md":"B_Z_uoz8","modules_sync_engine.md":"KNdJODq0","modules_sync_examples.md":"C2necAC8","modules_sync_index.md":"CMse09Zj","modules_sync_operation.md":"CW7cXwiY","modules_sync_outbox.md":"BEWlfgkw","modules_sync_retry_policy.md":"BkjRd7eg","modules_sync_wal.md":"n1pr6CKb","modules_time_guide.md":"CQUjxlqt","modules_time_index.md":"C8KWyJFT","modules_utils_env.md":"C_0WuoWB","modules_utils_index.md":"CjcdWwqY","modules_utils_logger.md":"CS5ffp2R","modules_utils_prettylogs.md":"R8BMarjn","modules_utils_result.md":"DKDoPkPD","modules_utils_string.md":"CILNsmli","modules_utils_time.md":"CCmktDit","modules_utils_uuid.md":"1H44NveG","modules_utils_validation.md":"BZ43PWKC","modules_validation_guide.md":"CfiTclGM","modules_validation_index.md":"ezCwtABG","modules_webrpc_examples.md":"DgNEuWzW","modules_webrpc_index.md":"DWzsAvxm","modules_websocket_api.md":"B9YH0fY0","modules_websocket_example-chat.md":"DAdNfmsu","modules_websocket_guide.md":"Cf2AoQp-","modules_websocket_index.md":"C5s6pLLe","project-setup.md":"Do_7wR3S","quick-start.md":"Cv5VDRFC","services_consulting.md":"Zyj1BwbV","services_index.md":"DuMmbpk4","services_support.md":"Cmt0L4WE","services_training.md":"BbkBFlYh"}
